{"bundler":"rollup","shimport":"1.0.1","assets":{"main":"client.581c55ed.js"},"css":{"main":"main.2430767647.css","chunks":{"index.svelte":["index.9b4f2a46.css","client.581c55ed.css"],"organizations/[id].svelte":["[id].528641c3.css","client.581c55ed.css"],"funds/[id].svelte":["[id].3820006b.css","client.581c55ed.css"],"lists/organizations.svelte":["client.581c55ed.css"],"lists/funds.svelte":["client.581c55ed.css"],"users/index.svelte":["client.581c55ed.css"],"users/me.svelte":["me.75c7d5ca.css","client.581c55ed.css"],"users/[id].svelte":["client.581c55ed.css"],"map/index.svelte":["client.581c55ed.css"],"map/[id].svelte":["client.581c55ed.css"]}},"legacy_assets":{"main":"client.adabbea9.js"}}